setup.py
catcfg.egg-info/PKG-INFO
catcfg.egg-info/SOURCES.txt
catcfg.egg-info/dependency_links.txt
catcfg.egg-info/entry_points.txt
catcfg.egg-info/requires.txt
catcfg.egg-info/top_level.txt
cfg/__init__.py
cfg/catconfig.py
cfg/db.py
cfg/tools.py