Metadata-Version: 1.0
Name: catcfg
Version: 0.1
Summary: catcfg: manage config data easily
Home-page: https://kowhoy.com
Author: kowhoy
Author-email: kowhoy@163.com
License: GPL
Keywords: catcfg,catconfig
Platform: Independant
